bye_wiki/__init__.py
bye_wiki/cli.py
bye_wiki-0.1.0.dist-info/LICENSE.txt
bye_wiki-0.1.0.dist-info/METADATA
bye_wiki-0.1.0.dist-info/WHEEL
bye_wiki-0.1.0.dist-info/entry_points.txt
bye_wiki-0.1.0.dist-info/top_level.txt
bye_wiki-0.1.0.dist-info/RECORD
