Metadata-Version: 2.1
Name: bye-wiki
Version: 0.1.0
Summary: Say goodbye to your wikis! Python command-line script to convert MediaWiki pages to other formats with pandoc
Home-page: https://github.com/jwflory/bw
Author: Justin W. Flory
Author-email: contact@jwf.io
License: BSD-3-Clause
Keywords: asciidoc,data,wiki,mediawiki,markdown,documentation,migration,pandoc
Classifier: License :: OSI Approved :: BSD License
Classifier: Operating System :: OS Independent
Classifier: Programming Language :: Python :: 3
Classifier: Programming Language :: Python :: 3.11
Requires-Python: >=3
License-File: LICENSE.txt
